<?xml version="1.0" encoding="utf-8"?>
<root extension=".bin">
	<object>
		<object id="972AF33C">
			<value id="0043F6F3" type="string">Sequences\f2_00a\f2_00a.seq</value>
			<value id="004D2372" type="string">Sequences\km06_13.seq</value>
			<value id="0184BB64" type="string">Sequences\f2m07_01.seq</value>
			<value id="05DF9D9F" type="string">Sequences\km02_02a1\km02_02a1_old.seq</value>
			<value id="06B44ADB" type="string">Sequences\race_cut01b\race_cut01b.seq</value>
			<value id="06C6C24D" type="string">Sequences\km03_00e\km03_00e.seq</value>
			<value id="074ED542" type="string">Sequences\km02_00\km02_00.seq</value>
			<value id="0851ED04" type="string">Sequences\f1s02b\f1s03b.seq</value>
			<value id="098A1F62" type="string">Sequences\f2s01\f2s01.seq</value>
			<value id="0D3DC62B" type="string">Sequences\km02_03\km02_03.seq</value>
			<value id="0DC35E46" type="string">Sequences\km06_11.seq</value>
			<value id="10F5A1F9" type="string">Sequences\f1_07\f1_11.seq</value>
			<value id="12DB1066" type="string">Sequences\f3m04\f3m04.seq</value>
			<value id="13466F79" type="string">Sequences\km07_05_02.seq</value>
			<value id="14EFB031" type="string">Sequences\km01_01.seq</value>
			<value id="1501AC2A" type="string">Sequences\f1_07\f1_08.seq</value>
			<value id="15182F59" type="string">Sequences\f3m06\f3m06.seq</value>
			<value id="15CCDD08" type="string">Sequences\km03_01b\km03_01b.seq</value>
			<value id="160814B9" type="string">Sequences\km03_04.seq</value>
			<value id="167FF8CA" type="string">Sequences\km03_00c\km03_00c.seq</value>
			<value id="16EAB683" type="string">Sequences\f2_03\f2_03.seq</value>
			<value id="1784D6FB" type="string">Sequences\km04_cs05.seq</value>
			<value id="17CF94C4" type="string">Sequences\f2m08_01.seq</value>
			<value id="1875EF3A" type="string">Sequences\f2m06_01.seq</value>
			<value id="18FE0A02" type="string">Sequences\f1s02b\f1s02b.seq</value>
			<value id="197E5751" type="string">Sequences\f3t08\f3t08.seq</value>
			<value id="1A36A618" type="string">Sequences\km05_03\km05_03.seq</value>
			<value id="1BD42D57" type="string">Sequences\f1t18\f1t18.seq</value>
			<value id="1C1DD22F" type="string">Sequences\f2m05_01\f2m08_01b.seq</value>
			<value id="1C8A96E9" type="string">Sequences\km05_02c\km05_02c.seq</value>
			<value id="1CDC220B" type="string">Sequences\f1_00b\f1_00b.seq</value>
			<value id="1DE14430" type="string">Sequences\km07_07\km07_07c.seq</value>
			<value id="1F63F4D8" type="string">Sequences\km06_02b\km06_02b.seq</value>
			<value id="201FC0A0" type="string">Sequences\km04_micro_01.seq</value>
			<value id="20F43C73" type="string">Sequences\km07_nuke.seq</value>
			<value id="20F89536" type="string">Sequences\km01_01c\km01_01c.seq</value>
			<value id="219331AB" type="string">Sequences\gen_ext_a\gen_ext_a.seq</value>
			<value id="22A349A9" type="string">Sequences\f1s02b\f1s07b.seq</value>
			<value id="22F58741" type="string">Sequences\km02_02a1\km02_02a1.seq</value>
			<value id="272334F3" type="string">Sequences\km01_01\km01_01.seq</value>
			<value id="28A45FCC" type="string">Sequences\f2t16\f2t16.seq</value>
			<value id="28E40A9F" type="string">Sequences\km07_07\km07_07.seq</value>
			<value id="29A3DA34" type="string">Sequences\km05_02b\km05_02b.seq</value>
			<value id="2AF97A55" type="string">Sequences\f2t03\f2t03.seq</value>
			<value id="2CF225ED" type="string">Sequences\km00_00\km00_00.seq</value>
			<value id="2EB5C3BF" type="string">Sequences\km03_03\km03_03.seq</value>
			<value id="2F108C8E" type="string">Sequences\km01_micro_01.seq</value>
			<value id="2F862E4E" type="string">Sequences\km03_01a\km03_01a.seq</value>
			<value id="2FCD978C" type="string">Sequences\f1m_03\f1m_07.seq</value>
			<value id="303FC117" type="string">Sequences\f1s02b\f2s07b.seq</value>
			<value id="30F1491C" type="string">Sequences\f1t16\f1t16.seq</value>
			<value id="3102D675" type="string">Sequences\km06_07.seq</value>
			<value id="33B51081" type="string">Sequences\f3t05\f3t05.seq</value>
			<value id="356273D1" type="string">Sequences\km06_qpr01_v3.seq</value>
			<value id="3568C564" type="string">Sequences\km05_04.seq</value>
			<value id="37B6B3E1" type="string">Sequences\gen_ext\gen_ext.seq</value>
			<value id="397E6CE4" type="string">Sequences\km07_01\km07_01.seq</value>
			<value id="3A7B052B" type="string">Sequences\km06_03\km06_03.seq</value>
			<value id="3E1874A8" type="string">Sequences\f3_03\f3_03.seq</value>
			<value id="3FEC412D" type="string">Sequences\f1_07\f1_07.seq</value>
			<value id="42AE9BC0" type="string">Sequences\km04_05\km04_05.seq</value>
			<value id="42FAE807" type="string">Sequences\f2m_07\f2m_07.seq</value>
			<value id="4552344F" type="string">Sequences\km04_cs01.seq</value>
			<value id="45D4B7AD" type="string">Sequences\km04_01\km04_01.seq</value>
			<value id="45DD4916" type="string">Sequences\km02_01.seq</value>
			<value id="45F47F41" type="string">Sequences\f2_07\f2_07.seq</value>
			<value id="46E89F46" type="string">Sequences\f1m03_01.seq</value>
			<value id="4719F325" type="string">Sequences\f3s01\f3s01.seq</value>
			<value id="48321CA0" type="string">Sequences\km01.placeholder2.seq</value>
			<value id="4869CA4E" type="string">Sequences\km03_00b\km03_00b.seq</value>
			<value id="4946D695" type="string">Sequences\km03_01c\km03_01c.seq</value>
			<value id="4A1B0284" type="string">Sequences\race_cut01a\race_cut01a.seq</value>
			<value id="4B5AE28C" type="string">Sequences\f1m08_03.seq</value>
			<value id="4DB738BF" type="string">Sequences\km06_09\km06_09.seq</value>
			<value id="4E623371" type="string">Sequences\f2m07_02.seq</value>
			<value id="4EA4BE78" type="string">Sequences\f1m08_02.seq</value>
			<value id="503A3590" type="string">Sequences\km06_08\km06_08.seq</value>
			<value id="51691737" type="string">Sequences\km03_00d\km03_00d.seq</value>
			<value id="537FC2B0" type="string">Sequences\km06_02\km06_02.seq</value>
			<value id="545A3A35" type="string">Sequences\f1_01\f1_01.seq</value>
			<value id="5494D5AD" type="string">Sequences\f2t15\f2t15.seq</value>
			<value id="55BC8411" type="string">Sequences\km00.seq</value>
			<value id="56D328F9" type="string">Sequences\f3_08\f3_08.seq</value>
			<value id="586CE0FA" type="string">Sequences\km06_12.seq</value>
			<value id="59D4E64E" type="string">Sequences\f1m07\f1m07.seq</value>
			<value id="5B7EDD84" type="string">Sequences\f2_01\f2_01.seq</value>
			<value id="5BF7192A" type="string">Sequences\km04_00\km04_00.seq</value>
			<value id="5C9118BC" type="string">Sequences\km01.placeholder1.seq</value>
			<value id="5F3D23F2" type="string">Sequences\f2_07\f2_11.seq</value>
			<value id="5F9302D7" type="string">Sequences\gen_ext_b\gen_ext_b.seq</value>
			<value id="5FCEA7A6" type="string">Sequences\km02_02.seq</value>
			<value id="6042F632" type="string">Sequences\f3_11\f3_11.seq</value>
			<value id="615CD943" type="string">Sequences\f1t13\f1t13.seq</value>
			<value id="61A42F98" type="string">Sequences\f2t10\f2t10.seq</value>
			<value id="62E43978" type="string">Sequences\f3m05_01\f3m05_01.seq</value>
			<value id="632A377B" type="string">Sequences\f1t05\f1t05.seq</value>
			<value id="63E24315" type="string">Sequences\f1m06_01.seq</value>
			<value id="65EA7444" type="string">Sequences\km02_02b\km02_02b.seq</value>
			<value id="6662DFCD" type="string">Sequences\f1t12\f1t12.seq</value>
			<value id="6668E65C" type="string">Sequences\f1s02\f1s02.seq</value>
			<value id="67A8952E" type="string">Sequences\fadeinfadeout_long.seq</value>
			<value id="680FF297" type="string">Sequences\km02_04.seq</value>
			<value id="6951385F" type="string">Sequences\km01_01b\km01_01b.seq</value>
			<value id="6A43D3DE" type="string">Sequences\f2m08_02.seq</value>
			<value id="6AACA7DF" type="string">Sequences\km06_qpr01.seq</value>
			<value id="6B306493" type="string">Sequences\f2t01\f2t01.seq</value>
			<value id="6C38B549" type="string">Sequences\Untitled1.seq</value>
			<value id="6D33C5A1" type="string">Sequences\km04_cs03.seq</value>
			<value id="6D6FAC87" type="string">Sequences\f1t04\f1t04.seq</value>
			<value id="6D86BD27" type="string">Sequences\f2_02\f2_02.seq</value>
			<value id="6F49F715" type="string">Sequences\f1_00a\f1_00a.seq</value>
			<value id="71CE9FCF" type="string">Sequences\km01_micro_02.seq</value>
			<value id="721DF1E7" type="string">Sequences\f2t12\f2t12.seq</value>
			<value id="734E76B0" type="string">Sequences\km02_03b\km02_03b.seq</value>
			<value id="75691988" type="string">Sequences\km05_02d\km05_02d.seq</value>
			<value id="75B63B74" type="string">Sequences\km01_03\km01_03.seq</value>
			<value id="767D550C" type="string">Sequences\race_cut01c\race_cut01c.seq</value>
			<value id="76C04588" type="string">Sequences\f3_01\f3_01.seq</value>
			<value id="78931B8A" type="string">Sequences\km02_micro_03.seq</value>
			<value id="7963A7A7" type="string">Sequences\f1_01b\f1_01b.seq</value>
			<value id="7C7F7AB6" type="string">Sequences\f2m05_01\f3m_04.seq</value>
			<value id="7D07C8A7" type="string">Sequences\f1s02b\f2s01b.seq</value>
			<value id="7D1281D3" type="string">Sequences\f3t15\f3t15.seq</value>
			<value id="7DB421AD" type="string">Sequences\f3_07\f3_07.seq</value>
			<value id="7DEA20CE" type="string">Sequences\km07_03.seq</value>
			<value id="7F10050A" type="string">Sequences\km04_08\km04_08.seq</value>
			<value id="800E7313" type="string">Sequences\f3t04\f3t04.seq</value>
			<value id="844FCB68" type="string">Sequences\f1m_03\f2m_01.seq</value>
			<value id="85C8ACC9" type="string">Sequences\f3t_01\f3t_01.seq</value>
			<value id="869102A0" type="string">Sequences\km07_07\km07_07b.seq</value>
			<value id="87391722" type="string">Sequences\km03_01.seq</value>
			<value id="874FB8B2" type="string">Sequences\km03_00a\km03_00a.seq</value>
			<value id="8784F079" type="string">Sequences\f2m_07\f3m_06.seq</value>
			<value id="8798F7BE" type="string">Sequences\f1_03\f1_03.seq</value>
			<value id="891BF9C3" type="string">Sequences\km07_02\km07_02.seq</value>
			<value id="8C6F2A2A" type="string">Sequences\km01_02\km01_02.seq</value>
			<value id="8E4FA63D" type="string">Sequences\f3t03\f3t03.seq</value>
			<value id="8F656DD8" type="string">Sequences\f1s02b\f3s01b.seq</value>
			<value id="92E8DA19" type="string">Sequences\f1t17\f1t17.seq</value>
			<value id="934CDB6C" type="string">Sequences\km02_02a\km02_02a.seq</value>
			<value id="935FBCCE" type="string">Sequences\f3s06\f3s06.seq</value>
			<value id="93C64183" type="string">Sequences\f3m02\f3m02.seq</value>
			<value id="948762D7" type="string">Sequences\km06_qpr02.seq</value>
			<value id="949FF156" type="string">Sequences\km06_03b\km06_03b.seq</value>
			<value id="94A7E896" type="string">Sequences\km06_10.seq</value>
			<value id="94AE2A8B" type="string">Sequences\f3t16\f3t16.seq</value>
			<value id="951E02CC" type="string">Sequences\f3m04_01.seq</value>
			<value id="953ABC0B" type="string">Sequences\km06_qpr01_v2.seq</value>
			<value id="96C0D82F" type="string">Sequences\gen_ext_c\gen_ext_c.seq</value>
			<value id="973A36F9" type="string">Sequences\km01_04.seq</value>
			<value id="99B9B3DA" type="string">Sequences\f3t01\f3t01.seq</value>
			<value id="9AD07352" type="string">Sequences\km06_04\km06_04.seq</value>
			<value id="9B7C5649" type="string">Sequences\f3_01b\f3_01b.seq</value>
			<value id="9BDF8B90" type="string">Sequences\km02_micro_02.seq</value>
			<value id="9CC91B82" type="string">Sequences\f2m01\f2m01.seq</value>
			<value id="9D5EA714" type="string">Sequences\f2s07\f2s07.seq</value>
			<value id="9DA3F75D" type="string">Sequences\f2_01b\f2_01b.seq</value>
			<value id="9E568AFD" type="string">Sequences\km06_04b\km06_04b.seq</value>
			<value id="9F22885E" type="string">Sequences\km02_02a\altejohan_km02_02a.seq</value>
			<value id="A1033165" type="string">Sequences\f3t09\f3t09.seq</value>
			<value id="A188FAB7" type="string">Sequences\f3_02\f3_02.seq</value>
			<value id="A313B72D" type="string">Sequences\race_cut01\race_cut01.seq</value>
			<value id="A38CA2FD" type="string">Sequences\f2t14\f2t14.seq</value>
			<value id="A3F37316" type="string">Sequences\km04_cs02.seq</value>
			<value id="A44C200F" type="string">Sequences\f3t14\f3t14.seq</value>
			<value id="A48C0FC5" type="string">Sequences\f3t12\f3t12.seq</value>
			<value id="A56A4D12" type="string">Sequences\f1t10\f1t10.seq</value>
			<value id="A63FDC89" type="string">Sequences\km04_00b\km04_00b.seq</value>
			<value id="A959537E" type="string">Sequences\km05_02e\km05_02e.seq</value>
			<value id="AB5F5937" type="string">Sequences\km07_04\km07_04.seq</value>
			<value id="AD5472B3" type="string">Sequences\km04_cs04.seq</value>
			<value id="AEE02C0B" type="string">Sequences\f1_07\f1_10.seq</value>
			<value id="B097FEFA" type="string">Sequences\km05_01b\km05_01b.seq</value>
			<value id="B0B78761" type="string">Sequences\km04_06\km04_06.seq</value>
			<value id="B159A537" type="string">Sequences\f2_07\f2_09.seq</value>
			<value id="B20E6211" type="string">Sequences\f2t08\f2t08.seq</value>
			<value id="B4629447" type="string">Sequences\f2t13\f2t13.seq</value>
			<value id="B769B33C" type="string">Sequences\km05_02a\km05_02a.seq</value>
			<value id="B856C3B5" type="string">Sequences\Untitled.seq</value>
			<value id="B9E58781" type="string">Sequences\f1s02b\f2s04b.seq</value>
			<value id="BA403D2C" type="string">Sequences\km04_03\km04_03.seq</value>
			<value id="BBC0B0DD" type="string">Sequences\f2_07\f2_08.seq</value>
			<value id="BCEC0644" type="string">Sequences\f3s04\f3s04.seq</value>
			<value id="BDE56626" type="string">Sequences\km01_01_workfile\km01_01_workfile.seq</value>
			<value id="BE44539C" type="string">Sequences\f2m05_01\f2m05_01.seq</value>
			<value id="BEB78E62" type="string">Sequences\f1s02b\f3s04b.seq</value>
			<value id="BF303C7F" type="string">Sequences\km06_14.seq</value>
			<value id="BFB1CC45" type="string">Sequences\f1s07\f1s07.seq</value>
			<value id="BFC2C2E8" type="string">Sequences\f1m03\f1m03.seq</value>
			<value id="C25DED68" type="string">Sequences\f2m05_micro_01.seq</value>
			<value id="C4473DD3" type="string">Sequences\f2m_07\f3m_02.seq</value>
			<value id="C46BD78F" type="string">Sequences\f3t13\f3t13.seq</value>
			<value id="C69B183B" type="string">Sequences\f2t11\f2t11.seq</value>
			<value id="C6E60DD6" type="string">Sequences\placeholder.seq</value>
			<value id="C9166FAC" type="string">Sequences\f1t09\f1t09.seq</value>
			<value id="C9764D4D" type="string">Sequences\f2t07\f2t07.seq</value>
			<value id="C9888D9D" type="string">Sequences\km07_06.seq</value>
			<value id="CAC29B56" type="string">Sequences\f1m_03\f1m_03.seq</value>
			<value id="CAD078E4" type="string">Sequences\race_start_cut01a\race_start_cut01a.seq</value>
			<value id="CB4B2254" type="string">Sequences\f2m07\f2m07.seq</value>
			<value id="CDCF4690" type="string">Sequences\km02_micro_01.seq</value>
			<value id="CE61E0EE" type="string">Sequences\km06_05.seq</value>
			<value id="D25DECA7" type="string">Sequences\f3t07\f3t07.seq</value>
			<value id="D2F4EA93" type="string">Sequences\km06_10\km06_10.seq</value>
			<value id="D5D6EB07" type="string">Sequences\f2s04\f2s04.seq</value>
			<value id="D7159CC9" type="string">Sequences\gen_ext_d\gen_ext_d.seq</value>
			<value id="D749914D" type="string">Sequences\km04_06b\km04_06b.seq</value>
			<value id="D8F75F9D" type="string">Sequences\km06_01\km06_01.seq</value>
			<value id="DA7AE271" type="string">Sequences\f2m_07\f3m05_01.seq</value>
			<value id="DE86A869" type="string">Sequences\fadeinfadeout.seq</value>
			<value id="DE8BDE99" type="string">Sequences\km05_02\km05_02.seq</value>
			<value id="E0B70403" type="string">Sequences\km01_00\km01_00.seq</value>
			<value id="E306CFA6" type="string">Sequences\f2m06_02.seq</value>
			<value id="E7678885" type="string">Sequences\benchmarks_win32\benchmark_1.seq</value>
			<value id="E98FE05B" type="string">Sequences\f1s02b\f3s06b.seq</value>
			<value id="EC889B63" type="string">Sequences\f3t11\f3t11.seq</value>
			<value id="EF53A666" type="string">Sequences\f2t09\f2t09.seq</value>
			<value id="EF5410A4" type="string">Sequences\f1_07\f1_09.seq</value>
			<value id="EFA72D9B" type="string">Sequences\f3_09\f3_09.seq</value>
			<value id="F1B54441" type="string">Sequences\f2t04\f2t04.seq</value>
			<value id="F41833A9" type="string">Sequences\f2t02\f2t02.seq</value>
			<value id="F41B51AA" type="string">Sequences\km05_01\km05_01.seq</value>
			<value id="F467B2D9" type="string">Sequences\f1t11\f1t11.seq</value>
			<value id="F48E421F" type="string">Sequences\f1m08_01.seq</value>
			<value id="F78AD94C" type="string">Sequences\f1s03\f1s03.seq</value>
			<value id="F8B429E0" type="string">Sequences\km07_05_01.seq</value>
			<value id="FC00EE1D" type="string">Sequences\f1_02\f1_02.seq</value>
			<value id="FD1005E2" type="string">Sequences\f2m06\f2m06.seq</value>
			<value id="FEACDBC7" type="string">Sequences\f2_00b\f2_00b.seq</value>
			<value id="FEDDCF58" type="string">Sequences\f3t06\f3t06.seq</value>
			<value id="FF78B0F7" type="string">Sequences\f2_07\f2_10.seq</value>
			<value id="FFDE1388" type="string">Sequences\f3_10\f3_10.seq</value>
		</object>
	</object>
</root>